moveshelf_api/__init__.py
moveshelf_api/api.py
moveshelf_api/util.py
moveshelf_api/utils/__init__.py
moveshelf_api/utils/hash.py
moveshelf_api-1.6.0.dist-info/METADATA
moveshelf_api-1.6.0.dist-info/WHEEL
moveshelf_api-1.6.0.dist-info/licenses/LICENSE
moveshelf_api-1.6.0.dist-info/RECORD
