Metadata-Version: 2.4
Name: moveshelf_api
Version: 1.6.0
Summary: Public package including the Python API
Project-URL: Homepage, https://github.com/moveshelf/moveshelf-python-api
Author-email: Moveshelf <info@moveshelf.com>
License-Expression: MIT
License-File: LICENSE
Classifier: Operating System :: OS Independent
Classifier: Programming Language :: Python :: 3
Requires-Python: >=3.9
Requires-Dist: crcmod~=1.7
Requires-Dist: six~=1.17
Requires-Dist: urllib3~=2.5
